fastapi_queue/__init__.py
fastapi_queue/gateway_manager.py
fastapi_queue/slowapi.py
fastapi_queue/utils.py
fastapi_queue/worker.py
fastapi_queue-0.1.1.dist-info/LICENSE
fastapi_queue-0.1.1.dist-info/METADATA
fastapi_queue-0.1.1.dist-info/WHEEL
fastapi_queue-0.1.1.dist-info/top_level.txt
fastapi_queue-0.1.1.dist-info/RECORD
