Metadata-Version: 2.1
Name: fastapi-queue
Version: 0.1.1
Summary: A task queue based on redis that can serve as a peak shaver and protect your app.
Home-page: https://github.com/GoodManWEN/fastapi-queue
Author: WEN
License: UNKNOWN
Keywords: fastapi-queue,fastapi,queue
Platform: UNKNOWN
Classifier: Programming Language :: Python :: 3
Classifier: Programming Language :: Python :: 3.7
Classifier: Programming Language :: Python :: 3.8
Classifier: Programming Language :: Python :: 3.9
Classifier: Programming Language :: Python :: 3.10
Classifier: License :: OSI Approved :: MIT License
Classifier: Operating System :: POSIX :: Linux
Classifier: Operating System :: Microsoft :: Windows
Classifier: Framework :: AsyncIO
Requires-Python: >=3.7
Requires-Dist: fastapi[standard]
Requires-Dist: ThreadPoolExecutorPlus
Requires-Dist: uvicorn
Requires-Dist: aioredis
Requires-Dist: msgpack (>=1.0.0)
Requires-Dist: loguru
